aiolimiter/__init__.py
aiolimiter/leakybucket.py
aiolimiter/py.typed
aiolimiter-1.2.0.dist-info/LICENSE.txt
aiolimiter-1.2.0.dist-info/METADATA
aiolimiter-1.2.0.dist-info/WHEEL
aiolimiter-1.2.0.dist-info/RECORD
