Metadata-Version: 2.1
Name: aiolimiter
Version: 1.2.0
Summary: asyncio rate limiter, a leaky bucket implementation
Home-page: https://github.com/mjpieters/aiolimiter
License: MIT
Keywords: asyncio,rate-limiting,leaky-bucket
Author: Martijn Pieters
Author-email: mj@zopatista.com
Requires-Python: >=3.8,<4.0
Classifier: Framework :: AsyncIO
Classifier: Intended Audience :: Developers
Classifier: License :: OSI Approved :: MIT License
Classifier: Programming Language :: Python :: 3
Classifier: Programming Language :: Python :: 3.8
Classifier: Programming Language :: Python :: 3.9
Classifier: Programming Language :: Python :: 3.10
Classifier: Programming Language :: Python :: 3.11
Classifier: Programming Language :: Python :: 3.12
Classifier: Programming Language :: Python :: 3.13
Project-URL: CI: Azure Pipelines, https://dev.azure.com/mjpieters/aiolimiter/_build
Project-URL: Coverage: codecov, https://codecov.io/github/aiolimiter/aiosignal
Project-URL: Documentation, http://aiolimiter.readthedocs.org/en/stable/
Project-URL: GitHub: issues, https://github.com/mjpieters/aiolimiter/issues
Project-URL: Repository, https://github.com/mjpieters/aiolimiter
